{
  "displayFieldName" : "",
  "fieldAliases" : {
    "FID" : "FID",
    "FID_AQUA_2" : "FID_AQUA_2",
    "PA_Str" : "PA_Str",
    "DMSLat" : "DMSLat",
    "DMSLon" : "DMSLon",
    "NAME" : "NAME",
    "PA_Str_1" : "PA_Str_1",
    "PA_Num_1" : "PA_Num_1"
  },
  "geometryType" : "esriGeometryPoint",
  "spatialReference" : {
    "wkid" : 4326,
    "latestWkid" : 4326
  },
  "fields" : [
    {
      "name" : "FID",
      "type" : "esriFieldTypeOID",
      "alias" : "FID"
    },
    {
      "name" : "FID_AQUA_2",
      "type" : "esriFieldTypeInteger",
      "alias" : "FID_AQUA_2"
    },
    {
      "name" : "PA_Str",
      "type" : "esriFieldTypeString",
      "alias" : "PA_Str",
      "length" : 3
    },
    {
      "name" : "DMSLat",
      "type" : "esriFieldTypeString",
      "alias" : "DMSLat",
      "length" : 254
    },
    {
      "name" : "DMSLon",
      "type" : "esriFieldTypeString",
      "alias" : "DMSLon",
      "length" : 254
    },
    {
      "name" : "NAME",
      "type" : "esriFieldTypeString",
      "alias" : "NAME",
      "length" : 50
    },
    {
      "name" : "PA_Str_1",
      "type" : "esriFieldTypeString",
      "alias" : "PA_Str_1",
      "length" : 3
    },
    {
      "name" : "PA_Num_1",
      "type" : "esriFieldTypeSmallInteger",
      "alias" : "PA_Num_1"
    }
  ],
  "features" : [
    {
      "attributes" : {
        "FID" : 13,
        "FID_AQUA_2" : -1,
        "PA_Str" : "14",
        "DMSLat" : "00°17'03.73\" LS",
        "DMSLon" : "123°17'47.84\" BT",
        "NAME" : "Titik ZPPI No. 1 (Zona 14)",
        "PA_Str_1" : "14",
        "PA_Num_1" : 14
      },
      "geometry" : {
        "x" : 123.29662296000004,
        "y" : -0.28437201599997053
      }
    },
    {
      "attributes" : {
        "FID" : 14,
        "FID_AQUA_2" : -1,
        "PA_Str" : "14",
        "DMSLat" : "00°14'36.68\" LS",
        "DMSLon" : "123°20'13.99\" BT",
        "NAME" : "Titik ZPPI No. 2 (Zona 14)",
        "PA_Str_1" : "14",
        "PA_Num_1" : 14
      },
      "geometry" : {
        "x" : 123.33722188200011,
        "y" : -0.24352483699995631
      }
    },
    {
      "attributes" : {
        "FID" : 15,
        "FID_AQUA_2" : -1,
        "PA_Str" : "14",
        "DMSLat" : "00°22'10.57\" LS",
        "DMSLon" : "123°20'59.68\" BT",
        "NAME" : "Titik ZPPI No. 3 (Zona 14)",
        "PA_Str_1" : "14",
        "PA_Num_1" : 14
      },
      "geometry" : {
        "x" : 123.34991383200007,
        "y" : -0.36960323599989664
      }
    },
    {
      "attributes" : {
        "FID" : 16,
        "FID_AQUA_2" : -1,
        "PA_Str" : "14",
        "DMSLat" : "00°15'09.36\" LS",
        "DMSLon" : "123°22'13.70\" BT",
        "NAME" : "Titik ZPPI No. 4 (Zona 14)",
        "PA_Str_1" : "14",
        "PA_Num_1" : 14
      },
      "geometry" : {
        "x" : 123.370473918,
        "y" : -0.25260235799990127
      }
    },
    {
      "attributes" : {
        "FID" : 17,
        "FID_AQUA_2" : -1,
        "PA_Str" : "14",
        "DMSLat" : "03°30'33.93\" LS",
        "DMSLon" : "123°25'00.90\" BT",
        "NAME" : "Titik ZPPI No. 5 (Zona 14)",
        "PA_Str_1" : "14",
        "PA_Num_1" : 14
      },
      "geometry" : {
        "x" : 123.41691763200006,
        "y" : -3.5094272889999605
      }
    },
    {
      "attributes" : {
        "FID" : 18,
        "FID_AQUA_2" : -1,
        "PA_Str" : "14",
        "DMSLat" : "00°17'15.92\" LS",
        "DMSLon" : "123°27'42.72\" BT",
        "NAME" : "Titik ZPPI No. 6 (Zona 14)",
        "PA_Str_1" : "14",
        "PA_Num_1" : 14
      },
      "geometry" : {
        "x" : 123.46186876700008,
        "y" : -0.28775614999993238
      }
    },
    {
      "attributes" : {
        "FID" : 19,
        "FID_AQUA_2" : -1,
        "PA_Str" : "14",
        "DMSLat" : "03°27'06.21\" LS",
        "DMSLon" : "123°29'55.77\" BT",
        "NAME" : "Titik ZPPI No. 7 (Zona 14)",
        "PA_Str_1" : "14",
        "PA_Num_1" : 14
      },
      "geometry" : {
        "x" : 123.49882508200005,
        "y" : -3.4517254550000036
      }
    },
    {
      "attributes" : {
        "FID" : 20,
        "FID_AQUA_2" : -1,
        "PA_Str" : "14",
        "DMSLat" : "02°33'55.30\" LS",
        "DMSLon" : "126°54'08.80\" BT",
        "NAME" : "Titik ZPPI No. 8 (Zona 14)",
        "PA_Str_1" : "14",
        "PA_Num_1" : 14
      },
      "geometry" : {
        "x" : 126.90244517100007,
        "y" : -2.5653631859999297
      }
    },
    {
      "attributes" : {
        "FID" : 21,
        "FID_AQUA_2" : -1,
        "PA_Str" : "14",
        "DMSLat" : "02°31'11.12\" LS",
        "DMSLon" : "126°55'36.72\" BT",
        "NAME" : "Titik ZPPI No. 9 (Zona 14)",
        "PA_Str_1" : "14",
        "PA_Num_1" : 14
      },
      "geometry" : {
        "x" : 126.92686917300014,
        "y" : -2.5197558709999672
      }
    },
    {
      "attributes" : {
        "FID" : 22,
        "FID_AQUA_2" : -1,
        "PA_Str" : "14",
        "DMSLat" : "02°32'03.66\" LS",
        "DMSLon" : "127°03'20.64\" BT",
        "NAME" : "Titik ZPPI No. 10 (Zona 14)",
        "PA_Str_1" : "14",
        "PA_Num_1" : 14
      },
      "geometry" : {
        "x" : 127.05573447100009,
        "y" : -2.5343520619999165
      }
    },
    {
      "attributes" : {
        "FID" : 23,
        "FID_AQUA_2" : -1,
        "PA_Str" : "14",
        "DMSLat" : "02°25'29.01\" LS",
        "DMSLon" : "127°11'58.71\" BT",
        "NAME" : "Titik ZPPI No. 11 (Zona 14)",
        "PA_Str_1" : "14",
        "PA_Num_1" : 14
      },
      "geometry" : {
        "x" : 127.19964182300012,
        "y" : -2.4247277579999942
      }
    }
  ]
}