{
  "displayFieldName" : "",
  "fieldAliases" : {
    "FID" : "FID",
    "FID_viirs_" : "FID_viirs_",
    "PA_Str" : "PA_Str",
    "DMSLat" : "DMSLat",
    "DMSLon" : "DMSLon",
    "NAME" : "NAME",
    "PA_Str_1" : "PA_Str_1",
    "PA_Num_1" : "PA_Num_1"
  },
  "geometryType" : "esriGeometryPoint",
  "spatialReference" : {
    "wkid" : 4326,
    "latestWkid" : 4326
  },
  "fields" : [
    {
      "name" : "FID",
      "type" : "esriFieldTypeOID",
      "alias" : "FID"
    },
    {
      "name" : "FID_viirs_",
      "type" : "esriFieldTypeInteger",
      "alias" : "FID_viirs_"
    },
    {
      "name" : "PA_Str",
      "type" : "esriFieldTypeString",
      "alias" : "PA_Str",
      "length" : 3
    },
    {
      "name" : "DMSLat",
      "type" : "esriFieldTypeString",
      "alias" : "DMSLat",
      "length" : 254
    },
    {
      "name" : "DMSLon",
      "type" : "esriFieldTypeString",
      "alias" : "DMSLon",
      "length" : 254
    },
    {
      "name" : "NAME",
      "type" : "esriFieldTypeString",
      "alias" : "NAME",
      "length" : 50
    },
    {
      "name" : "PA_Str_1",
      "type" : "esriFieldTypeString",
      "alias" : "PA_Str_1",
      "length" : 3
    },
    {
      "name" : "PA_Num_1",
      "type" : "esriFieldTypeSmallInteger",
      "alias" : "PA_Num_1"
    }
  ],
  "features" : [
    {
      "attributes" : {
        "FID" : 39,
        "FID_viirs_" : -1,
        "PA_Str" : "6",
        "DMSLat" : "06°46'42.49\" LU",
        "DMSLon" : "122°51'46.00\" BT",
        "NAME" : "Titik ZPPI No. 1 (Zona 6)",
        "PA_Str_1" : "6",
        "PA_Num_1" : 6
      },
      "geometry" : {
        "x" : 122.86278017100008,
        "y" : 6.7784695410000175
      }
    },
    {
      "attributes" : {
        "FID" : 40,
        "FID_viirs_" : -1,
        "PA_Str" : "6",
        "DMSLat" : "06°46'08.51\" LU",
        "DMSLon" : "123°00'01.71\" BT",
        "NAME" : "Titik ZPPI No. 2 (Zona 6)",
        "PA_Str_1" : "6",
        "PA_Num_1" : 6
      },
      "geometry" : {
        "x" : 123.00047645000009,
        "y" : 6.7690312660000664
      }
    },
    {
      "attributes" : {
        "FID" : 41,
        "FID_viirs_" : -1,
        "PA_Str" : "6",
        "DMSLat" : "06°13'44.56\" LU",
        "DMSLon" : "123°17'35.17\" BT",
        "NAME" : "Titik ZPPI No. 3 (Zona 6)",
        "PA_Str_1" : "6",
        "PA_Num_1" : 6
      },
      "geometry" : {
        "x" : 123.29310465500006,
        "y" : 6.2290451870000787
      }
    },
    {
      "attributes" : {
        "FID" : 42,
        "FID_viirs_" : -1,
        "PA_Str" : "6",
        "DMSLat" : "06°49'18.63\" LU",
        "DMSLon" : "123°17'49.22\" BT",
        "NAME" : "Titik ZPPI No. 4 (Zona 6)",
        "PA_Str_1" : "6",
        "PA_Num_1" : 6
      },
      "geometry" : {
        "x" : 123.297005826,
        "y" : 6.8218431849999952
      }
    },
    {
      "attributes" : {
        "FID" : 43,
        "FID_viirs_" : -1,
        "PA_Str" : "6",
        "DMSLat" : "06°57'24.11\" LU",
        "DMSLon" : "123°19'52.76\" BT",
        "NAME" : "Titik ZPPI No. 5 (Zona 6)",
        "PA_Str_1" : "6",
        "PA_Num_1" : 6
      },
      "geometry" : {
        "x" : 123.33132346400012,
        "y" : 6.9566999870000004
      }
    },
    {
      "attributes" : {
        "FID" : 44,
        "FID_viirs_" : -1,
        "PA_Str" : "6",
        "DMSLat" : "06°16'16.25\" LU",
        "DMSLon" : "123°22'42.61\" BT",
        "NAME" : "Titik ZPPI No. 6 (Zona 6)",
        "PA_Str_1" : "6",
        "PA_Num_1" : 6
      },
      "geometry" : {
        "x" : 123.37850369000012,
        "y" : 6.271181100000053
      }
    },
    {
      "attributes" : {
        "FID" : 45,
        "FID_viirs_" : -1,
        "PA_Str" : "6",
        "DMSLat" : "05°55'48.22\" LU",
        "DMSLon" : "123°25'58.96\" BT",
        "NAME" : "Titik ZPPI No. 7 (Zona 6)",
        "PA_Str_1" : "6",
        "PA_Num_1" : 6
      },
      "geometry" : {
        "x" : 123.43304662500009,
        "y" : 5.9300627610000625
      }
    },
    {
      "attributes" : {
        "FID" : 46,
        "FID_viirs_" : -1,
        "PA_Str" : "6",
        "DMSLat" : "06°01'53.66\" LU",
        "DMSLon" : "123°25'59.71\" BT",
        "NAME" : "Titik ZPPI No. 8 (Zona 6)",
        "PA_Str_1" : "6",
        "PA_Num_1" : 6
      },
      "geometry" : {
        "x" : 123.43325480100009,
        "y" : 6.0315737320000586
      }
    },
    {
      "attributes" : {
        "FID" : 47,
        "FID_viirs_" : -1,
        "PA_Str" : "6",
        "DMSLat" : "06°01'52.17\" LU",
        "DMSLon" : "123°33'21.64\" BT",
        "NAME" : "Titik ZPPI No. 9 (Zona 6)",
        "PA_Str_1" : "6",
        "PA_Num_1" : 6
      },
      "geometry" : {
        "x" : 123.55601335800006,
        "y" : 6.0311610990000233
      }
    },
    {
      "attributes" : {
        "FID" : 48,
        "FID_viirs_" : -1,
        "PA_Str" : "6",
        "DMSLat" : "06°44'36.53\" LU",
        "DMSLon" : "123°43'31.67\" BT",
        "NAME" : "Titik ZPPI No. 10 (Zona 6)",
        "PA_Str_1" : "6",
        "PA_Num_1" : 6
      },
      "geometry" : {
        "x" : 123.72546663300008,
        "y" : 6.7434810930000779
      }
    },
    {
      "attributes" : {
        "FID" : 49,
        "FID_viirs_" : -1,
        "PA_Str" : "6",
        "DMSLat" : "06°43'56.33\" LU",
        "DMSLon" : "123°48'49.34\" BT",
        "NAME" : "Titik ZPPI No. 11 (Zona 6)",
        "PA_Str_1" : "6",
        "PA_Num_1" : 6
      },
      "geometry" : {
        "x" : 123.81370628800005,
        "y" : 6.7323147250000517
      }
    },
    {
      "attributes" : {
        "FID" : 50,
        "FID_viirs_" : -1,
        "PA_Str" : "6",
        "DMSLat" : "05°57'18.84\" LU",
        "DMSLon" : "123°49'39.86\" BT",
        "NAME" : "Titik ZPPI No. 12 (Zona 6)",
        "PA_Str_1" : "6",
        "PA_Num_1" : 6
      },
      "geometry" : {
        "x" : 123.82773976400009,
        "y" : 5.9552341000000588
      }
    },
    {
      "attributes" : {
        "FID" : 51,
        "FID_viirs_" : -1,
        "PA_Str" : "6",
        "DMSLat" : "06°04'07.73\" LU",
        "DMSLon" : "123°54'28.25\" BT",
        "NAME" : "Titik ZPPI No. 13 (Zona 6)",
        "PA_Str_1" : "6",
        "PA_Num_1" : 6
      },
      "geometry" : {
        "x" : 123.90784976200011,
        "y" : 6.0688162380000712
      }
    },
    {
      "attributes" : {
        "FID" : 52,
        "FID_viirs_" : -1,
        "PA_Str" : "6",
        "DMSLat" : "05°51'05.89\" LU",
        "DMSLon" : "123°57'15.34\" BT",
        "NAME" : "Titik ZPPI No. 14 (Zona 6)",
        "PA_Str_1" : "6",
        "PA_Num_1" : 6
      },
      "geometry" : {
        "x" : 123.95426306000006,
        "y" : 5.8516387969999997
      }
    },
    {
      "attributes" : {
        "FID" : 53,
        "FID_viirs_" : -1,
        "PA_Str" : "6",
        "DMSLat" : "05°56'04.36\" LU",
        "DMSLon" : "124°00'56.46\" BT",
        "NAME" : "Titik ZPPI No. 15 (Zona 6)",
        "PA_Str_1" : "6",
        "PA_Num_1" : 6
      },
      "geometry" : {
        "x" : 124.01568607600007,
        "y" : 5.9345452030000381
      }
    },
    {
      "attributes" : {
        "FID" : 54,
        "FID_viirs_" : -1,
        "PA_Str" : "6",
        "DMSLat" : "05°49'38.87\" LU",
        "DMSLon" : "124°06'49.67\" BT",
        "NAME" : "Titik ZPPI No. 16 (Zona 6)",
        "PA_Str_1" : "6",
        "PA_Num_1" : 6
      },
      "geometry" : {
        "x" : 124.11379955400005,
        "y" : 5.8274665730000699
      }
    },
    {
      "attributes" : {
        "FID" : 55,
        "FID_viirs_" : -1,
        "PA_Str" : "6",
        "DMSLat" : "05°45'36.46\" LU",
        "DMSLon" : "124°10'58.00\" BT",
        "NAME" : "Titik ZPPI No. 17 (Zona 6)",
        "PA_Str_1" : "6",
        "PA_Num_1" : 6
      },
      "geometry" : {
        "x" : 124.18277987200008,
        "y" : 5.760128344000023
      }
    },
    {
      "attributes" : {
        "FID" : 56,
        "FID_viirs_" : -1,
        "PA_Str" : "6",
        "DMSLat" : "05°36'48.90\" LU",
        "DMSLon" : "124°18'20.23\" BT",
        "NAME" : "Titik ZPPI No. 18 (Zona 6)",
        "PA_Str_1" : "6",
        "PA_Num_1" : 6
      },
      "geometry" : {
        "x" : 124.30562041100009,
        "y" : 5.6135835509999978
      }
    },
    {
      "attributes" : {
        "FID" : 57,
        "FID_viirs_" : -1,
        "PA_Str" : "6",
        "DMSLat" : "05°26'10.63\" LU",
        "DMSLon" : "124°23'00.03\" BT",
        "NAME" : "Titik ZPPI No. 19 (Zona 6)",
        "PA_Str_1" : "6",
        "PA_Num_1" : 6
      },
      "geometry" : {
        "x" : 124.38334207700004,
        "y" : 5.4362883880000403
      }
    },
    {
      "attributes" : {
        "FID" : 58,
        "FID_viirs_" : -1,
        "PA_Str" : "6",
        "DMSLat" : "05°19'14.44\" LU",
        "DMSLon" : "124°28'07.44\" BT",
        "NAME" : "Titik ZPPI No. 20 (Zona 6)",
        "PA_Str_1" : "6",
        "PA_Num_1" : 6
      },
      "geometry" : {
        "x" : 124.46873387800011,
        "y" : 5.320680441000011
      }
    },
    {
      "attributes" : {
        "FID" : 59,
        "FID_viirs_" : -1,
        "PA_Str" : "6",
        "DMSLat" : "05°39'50.96\" LU",
        "DMSLon" : "125°40'48.96\" BT",
        "NAME" : "Titik ZPPI No. 21 (Zona 6)",
        "PA_Str_1" : "6",
        "PA_Num_1" : 6
      },
      "geometry" : {
        "x" : 125.68026797000005,
        "y" : 5.664157232000008
      }
    },
    {
      "attributes" : {
        "FID" : 60,
        "FID_viirs_" : -1,
        "PA_Str" : "6",
        "DMSLat" : "05°41'07.14\" LU",
        "DMSLon" : "125°41'35.97\" BT",
        "NAME" : "Titik ZPPI No. 22 (Zona 6)",
        "PA_Str_1" : "6",
        "PA_Num_1" : 6
      },
      "geometry" : {
        "x" : 125.69332701100009,
        "y" : 5.6853185020000332
      }
    },
    {
      "attributes" : {
        "FID" : 61,
        "FID_viirs_" : -1,
        "PA_Str" : "6",
        "DMSLat" : "05°38'51.25\" LU",
        "DMSLon" : "125°42'01.66\" BT",
        "NAME" : "Titik ZPPI No. 23 (Zona 6)",
        "PA_Str_1" : "6",
        "PA_Num_1" : 6
      },
      "geometry" : {
        "x" : 125.70046329500008,
        "y" : 5.6475711019999899
      }
    },
    {
      "attributes" : {
        "FID" : 62,
        "FID_viirs_" : -1,
        "PA_Str" : "6",
        "DMSLat" : "05°53'24.37\" LU",
        "DMSLon" : "125°50'07.47\" BT",
        "NAME" : "Titik ZPPI No. 24 (Zona 6)",
        "PA_Str_1" : "6",
        "PA_Num_1" : 6
      },
      "geometry" : {
        "x" : 125.83540916400008,
        "y" : 5.8901052000000256
      }
    },
    {
      "attributes" : {
        "FID" : 63,
        "FID_viirs_" : -1,
        "PA_Str" : "6",
        "DMSLat" : "05°46'29.08\" LU",
        "DMSLon" : "126°00'32.52\" BT",
        "NAME" : "Titik ZPPI No. 25 (Zona 6)",
        "PA_Str_1" : "6",
        "PA_Num_1" : 6
      },
      "geometry" : {
        "x" : 126.00903363100008,
        "y" : 5.77474659500011
      }
    },
    {
      "attributes" : {
        "FID" : 64,
        "FID_viirs_" : -1,
        "PA_Str" : "6",
        "DMSLat" : "05°52'37.65\" LU",
        "DMSLon" : "126°00'48.32\" BT",
        "NAME" : "Titik ZPPI No. 26 (Zona 6)",
        "PA_Str_1" : "6",
        "PA_Num_1" : 6
      },
      "geometry" : {
        "x" : 126.01342247000005,
        "y" : 5.8771267689999931
      }
    },
    {
      "attributes" : {
        "FID" : 65,
        "FID_viirs_" : -1,
        "PA_Str" : "6",
        "DMSLat" : "06°07'01.05\" LU",
        "DMSLon" : "126°01'05.48\" BT",
        "NAME" : "Titik ZPPI No. 27 (Zona 6)",
        "PA_Str_1" : "6",
        "PA_Num_1" : 6
      },
      "geometry" : {
        "x" : 126.01819040900011,
        "y" : 6.1169605370000681
      }
    },
    {
      "attributes" : {
        "FID" : 66,
        "FID_viirs_" : -1,
        "PA_Str" : "6",
        "DMSLat" : "05°50'19.31\" LU",
        "DMSLon" : "126°01'30.25\" BT",
        "NAME" : "Titik ZPPI No. 28 (Zona 6)",
        "PA_Str_1" : "6",
        "PA_Num_1" : 6
      },
      "geometry" : {
        "x" : 126.02506982000008,
        "y" : 5.8386985790000203
      }
    },
    {
      "attributes" : {
        "FID" : 67,
        "FID_viirs_" : -1,
        "PA_Str" : "6",
        "DMSLat" : "05°05'02.66\" LU",
        "DMSLon" : "126°02'34.62\" BT",
        "NAME" : "Titik ZPPI No. 29 (Zona 6)",
        "PA_Str_1" : "6",
        "PA_Num_1" : 6
      },
      "geometry" : {
        "x" : 126.04295107200005,
        "y" : 5.0840746280000317
      }
    },
    {
      "attributes" : {
        "FID" : 68,
        "FID_viirs_" : -1,
        "PA_Str" : "6",
        "DMSLat" : "05°09'55.56\" LU",
        "DMSLon" : "126°03'08.17\" BT",
        "NAME" : "Titik ZPPI No. 30 (Zona 6)",
        "PA_Str_1" : "6",
        "PA_Num_1" : 6
      },
      "geometry" : {
        "x" : 126.052271225,
        "y" : 5.1654359610000391
      }
    },
    {
      "attributes" : {
        "FID" : 69,
        "FID_viirs_" : -1,
        "PA_Str" : "6",
        "DMSLat" : "06°13'21.94\" LU",
        "DMSLon" : "126°05'41.57\" BT",
        "NAME" : "Titik ZPPI No. 31 (Zona 6)",
        "PA_Str_1" : "6",
        "PA_Num_1" : 6
      },
      "geometry" : {
        "x" : 126.09488132600003,
        "y" : 6.2227625450000126
      }
    },
    {
      "attributes" : {
        "FID" : 70,
        "FID_viirs_" : -1,
        "PA_Str" : "6",
        "DMSLat" : "05°41'12.41\" LU",
        "DMSLon" : "126°07'15.31\" BT",
        "NAME" : "Titik ZPPI No. 32 (Zona 6)",
        "PA_Str_1" : "6",
        "PA_Num_1" : 6
      },
      "geometry" : {
        "x" : 126.12092034800006,
        "y" : 5.686783100000067
      }
    },
    {
      "attributes" : {
        "FID" : 71,
        "FID_viirs_" : -1,
        "PA_Str" : "6",
        "DMSLat" : "05°29'18.23\" LU",
        "DMSLon" : "126°07'53.93\" BT",
        "NAME" : "Titik ZPPI No. 33 (Zona 6)",
        "PA_Str_1" : "6",
        "PA_Num_1" : 6
      },
      "geometry" : {
        "x" : 126.1316497900001,
        "y" : 5.4883974879999933
      }
    },
    {
      "attributes" : {
        "FID" : 72,
        "FID_viirs_" : -1,
        "PA_Str" : "6",
        "DMSLat" : "06°06'49.95\" LU",
        "DMSLon" : "126°08'01.82\" BT",
        "NAME" : "Titik ZPPI No. 34 (Zona 6)",
        "PA_Str_1" : "6",
        "PA_Num_1" : 6
      },
      "geometry" : {
        "x" : 126.13384086300002,
        "y" : 6.1138755980000816
      }
    },
    {
      "attributes" : {
        "FID" : 73,
        "FID_viirs_" : -1,
        "PA_Str" : "6",
        "DMSLat" : "05°11'55.73\" LU",
        "DMSLon" : "126°13'20.74\" BT",
        "NAME" : "Titik ZPPI No. 35 (Zona 6)",
        "PA_Str_1" : "6",
        "PA_Num_1" : 6
      },
      "geometry" : {
        "x" : 126.22242947200009,
        "y" : 5.1988145770000962
      }
    },
    {
      "attributes" : {
        "FID" : 74,
        "FID_viirs_" : -1,
        "PA_Str" : "6",
        "DMSLat" : "05°39'46.63\" LU",
        "DMSLon" : "126°15'34.26\" BT",
        "NAME" : "Titik ZPPI No. 36 (Zona 6)",
        "PA_Str_1" : "6",
        "PA_Num_1" : 6
      },
      "geometry" : {
        "x" : 126.25951921100007,
        "y" : 5.6629552250001183
      }
    },
    {
      "attributes" : {
        "FID" : 75,
        "FID_viirs_" : -1,
        "PA_Str" : "6",
        "DMSLat" : "05°28'31.67\" LU",
        "DMSLon" : "126°16'23.43\" BT",
        "NAME" : "Titik ZPPI No. 37 (Zona 6)",
        "PA_Str_1" : "6",
        "PA_Num_1" : 6
      },
      "geometry" : {
        "x" : 126.27317545500014,
        "y" : 5.475464703000096
      }
    },
    {
      "attributes" : {
        "FID" : 76,
        "FID_viirs_" : -1,
        "PA_Str" : "6",
        "DMSLat" : "05°37'15.47\" LU",
        "DMSLon" : "126°17'22.82\" BT",
        "NAME" : "Titik ZPPI No. 38 (Zona 6)",
        "PA_Str_1" : "6",
        "PA_Num_1" : 6
      },
      "geometry" : {
        "x" : 126.28967400800002,
        "y" : 5.6209650760000365
      }
    },
    {
      "attributes" : {
        "FID" : 77,
        "FID_viirs_" : -1,
        "PA_Str" : "6",
        "DMSLat" : "06°29'32.32\" LU",
        "DMSLon" : "126°22'23.94\" BT",
        "NAME" : "Titik ZPPI No. 39 (Zona 6)",
        "PA_Str_1" : "6",
        "PA_Num_1" : 6
      },
      "geometry" : {
        "x" : 126.37331759400004,
        "y" : 6.4923116690000917
      }
    },
    {
      "attributes" : {
        "FID" : 78,
        "FID_viirs_" : -1,
        "PA_Str" : "6",
        "DMSLat" : "03°09'49.42\" LU",
        "DMSLon" : "126°26'22.81\" BT",
        "NAME" : "Titik ZPPI No. 40 (Zona 6)",
        "PA_Str_1" : "6",
        "PA_Num_1" : 6
      },
      "geometry" : {
        "x" : 126.43966959900001,
        "y" : 3.1637298670000504
      }
    },
    {
      "attributes" : {
        "FID" : 79,
        "FID_viirs_" : -1,
        "PA_Str" : "6",
        "DMSLat" : "06°24'44.75\" LU",
        "DMSLon" : "126°27'57.16\" BT",
        "NAME" : "Titik ZPPI No. 41 (Zona 6)",
        "PA_Str_1" : "6",
        "PA_Num_1" : 6
      },
      "geometry" : {
        "x" : 126.46587975300008,
        "y" : 6.4124322390000401
      }
    },
    {
      "attributes" : {
        "FID" : 80,
        "FID_viirs_" : -1,
        "PA_Str" : "6",
        "DMSLat" : "06°42'18.59\" LU",
        "DMSLon" : "126°39'47.76\" BT",
        "NAME" : "Titik ZPPI No. 42 (Zona 6)",
        "PA_Str_1" : "6",
        "PA_Num_1" : 6
      },
      "geometry" : {
        "x" : 126.66326765700012,
        "y" : 6.7051648200000393
      }
    },
    {
      "attributes" : {
        "FID" : 81,
        "FID_viirs_" : -1,
        "PA_Str" : "6",
        "DMSLat" : "06°49'48.17\" LU",
        "DMSLon" : "126°45'46.08\" BT",
        "NAME" : "Titik ZPPI No. 43 (Zona 6)",
        "PA_Str_1" : "6",
        "PA_Num_1" : 6
      },
      "geometry" : {
        "x" : 126.76280219000009,
        "y" : 6.8300478060000138
      }
    },
    {
      "attributes" : {
        "FID" : 82,
        "FID_viirs_" : -1,
        "PA_Str" : "6",
        "DMSLat" : "03°42'42.65\" LU",
        "DMSLon" : "127°11'19.31\" BT",
        "NAME" : "Titik ZPPI No. 44 (Zona 6)",
        "PA_Str_1" : "6",
        "PA_Num_1" : 6
      },
      "geometry" : {
        "x" : 127.18869737899999,
        "y" : 3.7118495000000387
      }
    },
    {
      "attributes" : {
        "FID" : 83,
        "FID_viirs_" : -1,
        "PA_Str" : "6",
        "DMSLat" : "03°30'00.40\" LU",
        "DMSLon" : "127°13'00.99\" BT",
        "NAME" : "Titik ZPPI No. 45 (Zona 6)",
        "PA_Str_1" : "6",
        "PA_Num_1" : 6
      },
      "geometry" : {
        "x" : 127.21694276800004,
        "y" : 3.5001122050000468
      }
    },
    {
      "attributes" : {
        "FID" : 84,
        "FID_viirs_" : -1,
        "PA_Str" : "6",
        "DMSLat" : "03°42'38.16\" LU",
        "DMSLon" : "127°18'39.92\" BT",
        "NAME" : "Titik ZPPI No. 46 (Zona 6)",
        "PA_Str_1" : "6",
        "PA_Num_1" : 6
      },
      "geometry" : {
        "x" : 127.31109104300005,
        "y" : 3.7106017800000082
      }
    },
    {
      "attributes" : {
        "FID" : 85,
        "FID_viirs_" : -1,
        "PA_Str" : "6",
        "DMSLat" : "03°30'00.96\" LU",
        "DMSLon" : "127°21'30.89\" BT",
        "NAME" : "Titik ZPPI No. 47 (Zona 6)",
        "PA_Str_1" : "6",
        "PA_Num_1" : 6
      },
      "geometry" : {
        "x" : 127.35858271400005,
        "y" : 3.5002674740000153
      }
    },
    {
      "attributes" : {
        "FID" : 86,
        "FID_viirs_" : -1,
        "PA_Str" : "6",
        "DMSLat" : "03°37'05.91\" LU",
        "DMSLon" : "127°22'53.09\" BT",
        "NAME" : "Titik ZPPI No. 48 (Zona 6)",
        "PA_Str_1" : "6",
        "PA_Num_1" : 6
      },
      "geometry" : {
        "x" : 127.38141493300012,
        "y" : 3.618310258000065
      }
    },
    {
      "attributes" : {
        "FID" : 87,
        "FID_viirs_" : -1,
        "PA_Str" : "6",
        "DMSLat" : "03°19'03.50\" LU",
        "DMSLon" : "127°23'42.73\" BT",
        "NAME" : "Titik ZPPI No. 49 (Zona 6)",
        "PA_Str_1" : "6",
        "PA_Num_1" : 6
      },
      "geometry" : {
        "x" : 127.39520379799998,
        "y" : 3.3176410200000142
      }
    },
    {
      "attributes" : {
        "FID" : 88,
        "FID_viirs_" : -1,
        "PA_Str" : "6",
        "DMSLat" : "05°59'05.39\" LU",
        "DMSLon" : "127°26'32.00\" BT",
        "NAME" : "Titik ZPPI No. 50 (Zona 6)",
        "PA_Str_1" : "6",
        "PA_Num_1" : 6
      },
      "geometry" : {
        "x" : 127.44222367800012,
        "y" : 5.9848318000000091
      }
    },
    {
      "attributes" : {
        "FID" : 89,
        "FID_viirs_" : -1,
        "PA_Str" : "6",
        "DMSLat" : "05°50'32.93\" LU",
        "DMSLon" : "127°32'05.64\" BT",
        "NAME" : "Titik ZPPI No. 51 (Zona 6)",
        "PA_Str_1" : "6",
        "PA_Num_1" : 6
      },
      "geometry" : {
        "x" : 127.53490103500009,
        "y" : 5.8424831720000761
      }
    },
    {
      "attributes" : {
        "FID" : 90,
        "FID_viirs_" : -1,
        "PA_Str" : "6",
        "DMSLat" : "03°26'22.59\" LU",
        "DMSLon" : "127°39'12.35\" BT",
        "NAME" : "Titik ZPPI No. 52 (Zona 6)",
        "PA_Str_1" : "6",
        "PA_Num_1" : 6
      },
      "geometry" : {
        "x" : 127.65343098600013,
        "y" : 3.4396098170000968
      }
    },
    {
      "attributes" : {
        "FID" : 91,
        "FID_viirs_" : -1,
        "PA_Str" : "6",
        "DMSLat" : "06°41'12.43\" LU",
        "DMSLon" : "127°39'32.80\" BT",
        "NAME" : "Titik ZPPI No. 53 (Zona 6)",
        "PA_Str_1" : "6",
        "PA_Num_1" : 6
      },
      "geometry" : {
        "x" : 127.65911181100014,
        "y" : 6.6867869820001005
      }
    },
    {
      "attributes" : {
        "FID" : 92,
        "FID_viirs_" : -1,
        "PA_Str" : "6",
        "DMSLat" : "03°28'53.59\" LU",
        "DMSLon" : "127°40'43.25\" BT",
        "NAME" : "Titik ZPPI No. 54 (Zona 6)",
        "PA_Str_1" : "6",
        "PA_Num_1" : 6
      },
      "geometry" : {
        "x" : 127.67868080700013,
        "y" : 3.481554702000075
      }
    },
    {
      "attributes" : {
        "FID" : 93,
        "FID_viirs_" : -1,
        "PA_Str" : "6",
        "DMSLat" : "06°38'32.17\" LU",
        "DMSLon" : "127°45'30.84\" BT",
        "NAME" : "Titik ZPPI No. 55 (Zona 6)",
        "PA_Str_1" : "6",
        "PA_Num_1" : 6
      },
      "geometry" : {
        "x" : 127.75856823800004,
        "y" : 6.6422706820000812
      }
    },
    {
      "attributes" : {
        "FID" : 94,
        "FID_viirs_" : -1,
        "PA_Str" : "6",
        "DMSLat" : "03°21'32.36\" LU",
        "DMSLon" : "127°54'28.92\" BT",
        "NAME" : "Titik ZPPI No. 56 (Zona 6)",
        "PA_Str_1" : "6",
        "PA_Num_1" : 6
      },
      "geometry" : {
        "x" : 127.90803420700001,
        "y" : 3.358989569000034
      }
    }
  ]
}